LICENSE.txt
MANIFEST.in
README.md
setup.py
django_easy_validation/__init__.py
django_easy_validation/validators.py
django_easy_validation.egg-info/PKG-INFO
django_easy_validation.egg-info/SOURCES.txt
django_easy_validation.egg-info/dependency_links.txt
django_easy_validation.egg-info/not-zip-safe
django_easy_validation.egg-info/top_level.txt